aat/__init__.py
aat/__main__.py
aat/_enums.so
aat/_version.py
aat/backtest.py
aat/binding.so
aat/callback.py
aat/config.py
aat/data_source.py
aat/define.py
aat/enums.py
aat/exceptions.py
aat/exchange.py
aat/execution.py
aat/logging.py
aat/main.py
aat/market_data.py
aat/order_book.py
aat/order_entry.py
aat/parser.py
aat/persistence.py
aat/query.py
aat/risk.py
aat/strategy.py
aat/structs.py
aat/trading.py
aat/utils.py
aat/aat/_enums.so
aat/aat/binding.so
aat/exchanges/__init__.py
aat/exchanges/coinbase.py
aat/exchanges/gemini.py
aat/exchanges/kraken.py
aat/exchanges/poloniex.py
aat/exchanges/synthetic.py
aat/strategies/buy_and_hold.py
aat/strategies/data_capture.py
aat/strategies/sma.py
aat/tests/__init__.py
aat/tests/aat_test
aat/tests/test_all.py
aat/tests/test_backtest.py
aat/tests/test_callback.py
aat/tests/test_config.py
aat/tests/test_custom_strategies.py
aat/tests/test_data_source.py
aat/tests/test_define.py
aat/tests/test_enums.py
aat/tests/test_exchange.py
aat/tests/test_execution.py
aat/tests/test_main.py
aat/tests/test_order_book.py
aat/tests/test_order_entry.py
aat/tests/test_parser.py
aat/tests/test_risk.py
aat/tests/test_strategy.py
aat/tests/test_structs.py
aat/tests/test_trading.py
aat/tests/test_utils.py
aat/tests/exchanges/__init__.py
aat/tests/exchanges/test_coinbase.py
aat/tests/exchanges/test_gemini.py
aat/tests/strategies/__init__.py
aat/tests/ui/__init__.py
aat/tests/ui/test_server.py
aat/tests/ui/handlers/__init__.py
aat/tests/ui/handlers/common.py
aat/tests/ui/handlers/test_accounts.py
aat/tests/ui/handlers/test_base.py
aat/tests/ui/handlers/test_exchanges.py
aat/tests/ui/handlers/test_html.py
aat/tests/ui/handlers/test_last_price.py
aat/tests/ui/handlers/test_strategies.py
aat/tests/ui/handlers/test_strategy_trade_request.py
aat/tests/ui/handlers/test_strategy_trade_response.py
aat/tests/ui/handlers/test_trades.py
aat/ui/__init__.py
aat/ui/server.py
aat/ui/assets/static/css/font-awesome.min.css
aat-0.0.3.dist-info/LICENSE
aat-0.0.3.dist-info/METADATA
aat-0.0.3.dist-info/WHEEL
aat-0.0.3.dist-info/entry_points.txt
aat-0.0.3.dist-info/top_level.txt
aat-0.0.3.dist-info/RECORD
