Metadata-Version: 2.1
Name: aat
Version: 0.0.3
Summary: Algorithmic trading library
Home-page: https://github.com/timkpaine/aat
Author: Tim Paine
Author-email: timothy.k.paine@gmail.com
License: Apache 2.0
Keywords: algorithmic trading cryptocurrencies
Platform: UNKNOWN
Classifier: Development Status :: 3 - Alpha
Classifier: Programming Language :: Python :: 3.6
Classifier: Programming Language :: Python :: 3.7
Classifier: Programming Language :: Python :: 3.8
Requires-Python: >=3.7
Requires-Dist: aiohttp (>=3.5.4)
Requires-Dist: aiostream (>=0.3.1)
Requires-Dist: ccxt (>=1.18.529)
Requires-Dist: cycler (>=0.10.0)
Requires-Dist: Jinja2 (>=2.10)
Requires-Dist: matplotlib (>=2.2.2)
Requires-Dist: numpy (>=1.14.5)
Requires-Dist: pandas (>=0.23.3)
Requires-Dist: perspective-python (<0.4.0,>=0.1.6)
Requires-Dist: pyarrow (>=0.11.1)
Requires-Dist: scipy (>=1.1.0)
Requires-Dist: seaborn (>=0.8.1)
Requires-Dist: sphinx (>=1.7.5)
Requires-Dist: six (>=1.10.0)
Requires-Dist: requests (>=2.13.0)
Requires-Dist: tornado (>=5.1)
Requires-Dist: traitlets (>=4.3.2)
Requires-Dist: ujson (>=1.35)
Requires-Dist: uvloop (>=0.12.2)
Requires-Dist: websocket-client (>=0.40.0)
Requires-Dist: yarl (==1.1.0)
Provides-Extra: dev
Requires-Dist: flake8 (>=3.7.8) ; extra == 'dev'
Requires-Dist: mock ; extra == 'dev'
Requires-Dist: pybind11 (>=2.4.0) ; extra == 'dev'
Requires-Dist: pytest (>=4.3.0) ; extra == 'dev'
Requires-Dist: pytest-cov (>=2.6.1) ; extra == 'dev'
Requires-Dist: Sphinx (>=1.8.4) ; extra == 'dev'
Requires-Dist: sphinx-markdown-builder (>=0.5.2) ; extra == 'dev'
Requires-Dist: aiohttp (>=3.5.4) ; extra == 'dev'
Requires-Dist: aiostream (>=0.3.1) ; extra == 'dev'
Requires-Dist: ccxt (>=1.18.529) ; extra == 'dev'
Requires-Dist: cycler (>=0.10.0) ; extra == 'dev'
Requires-Dist: Jinja2 (>=2.10) ; extra == 'dev'
Requires-Dist: matplotlib (>=2.2.2) ; extra == 'dev'
Requires-Dist: numpy (>=1.14.5) ; extra == 'dev'
Requires-Dist: pandas (>=0.23.3) ; extra == 'dev'
Requires-Dist: perspective-python (<0.4.0,>=0.1.6) ; extra == 'dev'
Requires-Dist: pyarrow (>=0.11.1) ; extra == 'dev'
Requires-Dist: scipy (>=1.1.0) ; extra == 'dev'
Requires-Dist: seaborn (>=0.8.1) ; extra == 'dev'
Requires-Dist: sphinx (>=1.7.5) ; extra == 'dev'
Requires-Dist: six (>=1.10.0) ; extra == 'dev'
Requires-Dist: requests (>=2.13.0) ; extra == 'dev'
Requires-Dist: tornado (>=5.1) ; extra == 'dev'
Requires-Dist: traitlets (>=4.3.2) ; extra == 'dev'
Requires-Dist: ujson (>=1.35) ; extra == 'dev'
Requires-Dist: uvloop (>=0.12.2) ; extra == 'dev'
Requires-Dist: websocket-client (>=0.40.0) ; extra == 'dev'
Requires-Dist: yarl (==1.1.0) ; extra == 'dev'
